{
  "id": "compliance-calendar-env",
  "name": "Compliance Calendar - Development",
  "values": [
    {
      "key": "baseUrl",
      "value": "http://localhost:5000",
      "type": "string",
      "enabled": true
    },
    {
      "key": "employerToken",
      "value": "",
      "type": "string",
      "enabled": true
    },
    {
      "key": "adminToken",
      "value": "",
      "type": "string",
      "enabled": true
    },
    {
      "key": "complianceCalendarId",
      "value": "",
      "type": "string",
      "enabled": true
    },
    {
      "key": "employerPhone",
      "value": "9876543210",
      "type": "string",
      "enabled": true
    },
    {
      "key": "employerEmail",
      "value": "company@example.com",
      "type": "string",
      "enabled": true
    }
  ],
  "_postman_variable_scope": "environment",
  "_postman_exported_at": "2024-01-02T00:00:00.000Z",
  "_postman_exported_using": "Postman/10.0"
}
